aiowsgi/__init__.py
aiowsgi/compat.py
aiowsgi/task.py
aiowsgi/thread.py
aiowsgi-0.8.dist-info/LICENSE
aiowsgi-0.8.dist-info/METADATA
aiowsgi-0.8.dist-info/WHEEL
aiowsgi-0.8.dist-info/entry_points.txt
aiowsgi-0.8.dist-info/top_level.txt
aiowsgi-0.8.dist-info/RECORD
