Metadata-Version: 2.1
Name: aiowsgi
Version: 0.8
Summary: minimalist wsgi server using asyncio
Home-page: https://github.com/gawel/aiowsgi/
Author: Gael Pasgrimaud
Author-email: gael@gawel.org
License: MIT
Platform: UNKNOWN
Classifier: Intended Audience :: Developers
Classifier: Programming Language :: Python :: 3
Classifier: License :: OSI Approved :: MIT License
License-File: LICENSE
Requires-Dist: six
Requires-Dist: waitress
Requires-Dist: webob
Provides-Extra: test
Requires-Dist: pytest ; extra == 'test'
Requires-Dist: six ; extra == 'test'
Requires-Dist: webtest ; extra == 'test'
Requires-Dist: coverage ; extra == 'test'
Requires-Dist: coveralls ; extra == 'test'
Requires-Dist: WSGIProxy2 ; extra == 'test'
